{
  "_fv": 21,
  "_type": "recipe",
  "definition": {
    "recipeType": "Crafting",
    "xpReward": 0.0,
    "cookingTime": 200,
    "recipeRetstackSize": 1,
    "group": "",
    "recipeShapeless": false,
    "recipeSlots": [
      {
        "value": ""
      },
      {
        "value": "Blocks.LOG#2"
      },
      {
        "value": ""
      },
      {
        "value": "Blocks.LOG#2"
      },
      {
        "value": "CUSTOM:BlankIgniter"
      },
      {
        "value": "Blocks.LOG#2"
      },
      {
        "value": ""
      },
      {
        "value": "Blocks.LOG#2"
      },
      {
        "value": ""
      }
    ],
    "recipeReturnStack": {
      "value": "CUSTOM:BirchLogDimension"
    },
    "name": "birch_ig_c",
    "namespace": "mod"
  }
}